{"results":[{"aya":"078","id":3010,"locale":"ug","sura":"026","text":"ئۇ مېنى ياراتقان، ئۇ مېنى ھىدايەت قىلىدۇ","translator":"Muhammad Saleh"},{"aya":"079","id":3011,"locale":"ug","sura":"026","text":"ئۇ مېنى تاماق بىلەن تەمىنلەيدۇ، ئۇسسۇلۇق بىلەن تەمىنلەيدۇ","translator":"Muhammad Saleh"},{"aya":"080","id":3012,"locale":"ug","sura":"026","text":"ئاغرىپ قالسام ئۇ مېنى ساقايتىدۇ","translator":"Muhammad Saleh"},{"aya":"081","id":3013,"locale":"ug","sura":"026","text":"ئۇ مېنى قەبزى روھ قىلىدۇ، كېيىن يەنە تىرىلدۈرىدۇ","translator":"Muhammad Saleh"},{"aya":"082","id":3014,"locale":"ug","sura":"026","text":"قىيامەت كۈنى ئۇنىڭ مېنىڭ خاتالىقلىرىمنى مەغپىرەت قىلىشىنى ئۈمىد قىلىمەن","translator":"Muhammad Saleh"},{"aya":"083","id":3015,"locale":"ug","sura":"026","text":"پەرۋەردىگارىم! ماڭا ئىلىم ھېكمەت ئاتا قىلغىن، مېنى ياخشىلارغا قوشقىن","translator":"Muhammad Saleh"},{"aya":"084","id":3016,"locale":"ug","sura":"026","text":"كېيىنكىلەر ئارىسىدا ياخشى نامىمنى قالدۇرغىن","translator":"Muhammad Saleh"}],"metadata":{"itemsPerPage":7,"pages":33,"previousPage":"/ug/s026-11.json","nextPage":"/ug/s026-13.json"}}