{"results":[{"aya":"022","id":5870,"locale":"ug","sura":"083","text":"ياخشىلار نېمەت ئىچىدە (يەنى جەننەتتە) بولىدۇ","translator":"Muhammad Saleh"},{"aya":"023","id":5871,"locale":"ug","sura":"083","text":"ئۇلار تەختلەر ئۈستىدە تۇرۇپ (اﷲ نىڭ جەننەتتە ئۇلارغا بەرگەن تۈرلۈك نېمەتلىرىگە) قارايدۇ","translator":"Muhammad Saleh"},{"aya":"024","id":5872,"locale":"ug","sura":"083","text":"ئۇلارغا قارايدىغان بولساڭ، نېمەتنىڭ (ئۇلارنىڭ چىرايلىرىدىن چىقىپ تۇرغان) ئەسىرىنى تونۇيسەن","translator":"Muhammad Saleh"},{"aya":"025","id":5873,"locale":"ug","sura":"083","text":"ئۇلار ئاغزى پېچەتلەنگەن ساپ شاراب بىلەن سۇغىرىلىدۇ، ئىچىشنىڭ ئاخىرىدا ئۇنىڭدىن ئىپارنىڭ ھىدى كېلىپ تۇرىدۇ. قىزىققۇچىلار شۇنىڭغا قىزىقسۇن!","translator":"Muhammad Saleh"},{"aya":"026","id":5874,"locale":"ug","sura":"083","text":"ئۇلار ئاغزى پېچەتلەنگەن ساپ شاراب بىلەن سۇغىرىلىدۇ، ئىچىشنىڭ ئاخىرىدا ئۇنىڭدىن ئىپارنىڭ ھىدى كېلىپ تۇرىدۇ. قىزىققۇچىلار شۇنىڭغا قىزىقسۇن!","translator":"Muhammad Saleh"},{"aya":"027","id":5875,"locale":"ug","sura":"083","text":"ئۇنىڭغا (يەنى ساپ شارابقا) تەسنىمنىڭ (سۈيى) ئارىلاشتۇرۇلغان","translator":"Muhammad Saleh"},{"aya":"028","id":5876,"locale":"ug","sura":"083","text":"تەسنىم جەننەتتىكى بىر بۇلاق بولۇپ، ئۇنىڭدىن اﷲ نىڭ يېقىن بەندىلىرى ئىچىدۇ","translator":"Muhammad Saleh"}],"metadata":{"itemsPerPage":7,"pages":6,"previousPage":"/ug/s083-3.json","nextPage":"/ug/s083-5.json"}}