{"results":[{"aya":"022","id":5822,"locale":"es","sura":"081","text":"[Sepan que] su compañero [el Profeta Mujámmad] no es un loco,","translator":"Muhammad Isa García"},{"aya":"023","id":5823,"locale":"es","sura":"081","text":"lo vio [al ángel Gabriel] en el horizonte claro,","translator":"Muhammad Isa García"},{"aya":"024","id":5824,"locale":"es","sura":"081","text":"no oculta nada de lo que le fue revelado.","translator":"Muhammad Isa García"},{"aya":"025","id":5825,"locale":"es","sura":"081","text":"[El Corán] no es la palabra de un demonio maldito.","translator":"Muhammad Isa García"},{"aya":"026","id":5826,"locale":"es","sura":"081","text":"¿A dónde irán [con ese argumento]?","translator":"Muhammad Isa García"},{"aya":"027","id":5827,"locale":"es","sura":"081","text":"[El Corán] es un Mensaje para toda la humanidad,","translator":"Muhammad Isa García"},{"aya":"028","id":5828,"locale":"es","sura":"081","text":"para que se encamine quien quiera.","translator":"Muhammad Isa García"}],"metadata":{"itemsPerPage":7,"pages":5,"previousPage":"/es/s081-3.json","nextPage":"/es/s081-5.json"}}