{"results":[{"aya":"001","id":6044,"locale":"es","sura":"091","text":"Juro por el Sol cuando resplandece,","translator":"Muhammad Isa García"},{"aya":"002","id":6045,"locale":"es","sura":"091","text":"por la Luna cuando lo refleja,","translator":"Muhammad Isa García"},{"aya":"003","id":6046,"locale":"es","sura":"091","text":"por el día cuando fulgura,","translator":"Muhammad Isa García"},{"aya":"004","id":6047,"locale":"es","sura":"091","text":"por la noche cuando cubre con su oscuridad,","translator":"Muhammad Isa García"},{"aya":"005","id":6048,"locale":"es","sura":"091","text":"por el cosmos y la creación maravillosa que hay en él,","translator":"Muhammad Isa García"},{"aya":"006","id":6049,"locale":"es","sura":"091","text":"por la Tierra y su vasta extensión,","translator":"Muhammad Isa García"},{"aya":"007","id":6050,"locale":"es","sura":"091","text":"por el alma y su armonía,","translator":"Muhammad Isa García"}],"metadata":{"itemsPerPage":7,"pages":3,"nextPage":"/es/s091-2.json"}}