{"results":[{"aya":"050","id":5029,"locale":"fr","sura":"056","text":"seront réunis pour le rendez-vous d'un jour connu».","translator":"Muhammad Hamidullah"},{"aya":"051","id":5030,"locale":"fr","sura":"056","text":"Et puis, vous, les égarés, qui traitiez (la Résurrection) de mensonge,","translator":"Muhammad Hamidullah"},{"aya":"052","id":5031,"locale":"fr","sura":"056","text":"vous mangerez certainement d'un arbre de Zaqqûm.","translator":"Muhammad Hamidullah"},{"aya":"053","id":5032,"locale":"fr","sura":"056","text":"vous vous en remplirez le ventre,","translator":"Muhammad Hamidullah"},{"aya":"054","id":5033,"locale":"fr","sura":"056","text":"puis vous boirez par-dessus cela de l'eau bouillante,","translator":"Muhammad Hamidullah"},{"aya":"055","id":5034,"locale":"fr","sura":"056","text":"vous en boirez comme boivent les chameaux assoiffés.","translator":"Muhammad Hamidullah"},{"aya":"056","id":5035,"locale":"fr","sura":"056","text":"Voilà le repas d'accueil qui leur sera servi, au jour de la Rétribution.","translator":"Muhammad Hamidullah"}],"metadata":{"itemsPerPage":7,"pages":14,"previousPage":"/fr/s056-7.json","nextPage":"/fr/s056-9.json"}}