{"results":[{"aya":"022","id":4868,"locale":"no","sura":"054","text":"Nå har Vi gjort Koranen lett tilgjengelig til formaning! Men finnes det noen som lar seg formane?","translator":"Einar Berg"},{"aya":"023","id":4869,"locale":"no","sura":"054","text":"Thamod forkastet advarslene, og sa:","translator":"Einar Berg"},{"aya":"024","id":4870,"locale":"no","sura":"054","text":"«Skal vi følge et vanlig menneske fra vår egen krets? Da ville vi sannelig befinne oss i villfarelse og galskap.","translator":"Einar Berg"},{"aya":"025","id":4871,"locale":"no","sura":"054","text":"Er formaningen blitt overlatt ham av oss alle? Nei, han er en frekk løgner.»","translator":"Einar Berg"},{"aya":"026","id":4872,"locale":"no","sura":"054","text":"Men, i morgen skal de få vite hvem som er den frekke løgner!","translator":"Einar Berg"},{"aya":"027","id":4873,"locale":"no","sura":"054","text":"Vi skal sende kamelhoppen som en prøvelse for dem. Så følg med, og bevar tålmodigheten!","translator":"Einar Berg"},{"aya":"028","id":4874,"locale":"no","sura":"054","text":"Fortell dem at vannet skal fordeles blant dem, hver rasjon i sin tid.","translator":"Einar Berg"}],"metadata":{"itemsPerPage":7,"pages":8,"previousPage":"/no/s054-3.json","nextPage":"/no/s054-5.json"}}