{"results":[{"aya":"043","id":2975,"locale":"th","sura":"026","text":"มูซาได้กล่าวแก่พวกเขาว่า “จงโยนซิสิ่งที่พวกท่านจะต้องโยน”","translator":"King Fahad Quran Complex"},{"aya":"044","id":2976,"locale":"th","sura":"026","text":"แล้วพวกเขาก็ได้โยนเชือกหลายเส้นของพวกเขาและไม้เท้าหลายอันของพวกเขา และพวกเขากล่าวว่า “ด้วยเกียติยศของฟิรเอาน์แท้จริงเราเป็นผู้ชนะอย่างแน่นอน”","translator":"King Fahad Quran Complex"},{"aya":"045","id":2977,"locale":"th","sura":"026","text":"ครั้นแล้วมูซาก็ได้โยนไม้เท้าของเขา ณ บัดนั้นมันได้กลืนสิ่งที่พวกเขาได้ลองมันขึ้น","translator":"King Fahad Quran Complex"},{"aya":"046","id":2978,"locale":"th","sura":"026","text":"พวกนักเล่นกลจึงก้มหัวลงกราบสุญูด","translator":"King Fahad Quran Complex"},{"aya":"047","id":2979,"locale":"th","sura":"026","text":"พวกเขากล่าวว่า “เราศรัทธาต่อพระเจ้าแห่งสากลโลก”","translator":"King Fahad Quran Complex"},{"aya":"048","id":2980,"locale":"th","sura":"026","text":"พระเจ้าของมูซา และฮารูน","translator":"King Fahad Quran Complex"},{"aya":"049","id":2981,"locale":"th","sura":"026","text":"เขากล่าวว่า พวกท่านศรัทธาต่อเขาก่อนที่ฉันจะอนุญาตแก่พวกท่านกระนั้นหรือ? แน่นอนเขาต้องเป็นหัวหน้าของพวกท่านซึ่งได้สอนการเล่นกลแก่พวกท่าน แล้วพวกท่านจะรู้ แน่นอนฉันจะตัดมือของพวกท่านและเท้าของพวกท่านสลับข้างกัน และแน่นอนฉันจะแขวนตรึงไว้ทั้งหมด","translator":"King Fahad Quran Complex"}],"metadata":{"itemsPerPage":7,"pages":33,"previousPage":"/th/s026-6.json","nextPage":"/th/s026-8.json"}}