{"results":[{"aya":"015","id":5510,"locale":"th","sura":"074","text":"แล้วเขายังโลภที่จะให้ข้าเพิ่มพูนแก่เขาอีก","translator":"King Fahad Quran Complex"},{"aya":"016","id":5511,"locale":"th","sura":"074","text":"เปล่าเลย ! เพราะว่าเขาเป็นผู้ดื้อรั้นต่อสัญญาณต่าง ๆ ของเรา","translator":"King Fahad Quran Complex"},{"aya":"017","id":5512,"locale":"th","sura":"074","text":"ในไม่ช้าข้าจะเพิ่มพูนความยากลำบากแก่เขา","translator":"King Fahad Quran Complex"},{"aya":"018","id":5513,"locale":"th","sura":"074","text":"แท้จริงเขาได้ใคร่ครวญและคาดคะเน","translator":"King Fahad Quran Complex"},{"aya":"019","id":5514,"locale":"th","sura":"074","text":"ดังนั้นเขาได้รับความหายนะ เขาจะคาดคะเนได้อย่างไร ?","translator":"King Fahad Quran Complex"},{"aya":"020","id":5515,"locale":"th","sura":"074","text":"แล้วเขาได้รับความหายนะ เขาจะคาดคะเนได้อย่างไร ?","translator":"King Fahad Quran Complex"},{"aya":"021","id":5516,"locale":"th","sura":"074","text":"แล้วเขาได้ตรึกตรอง","translator":"King Fahad Quran Complex"}],"metadata":{"itemsPerPage":7,"pages":8,"previousPage":"/th/s074-2.json","nextPage":"/th/s074-4.json"}}