{"results":[{"aya":"008","id":5837,"locale":"dv","sura":"082","text":"އެކަލާނގެ އިރާދަކުރެއްވި ކޮންމެ ސިފަޔަކަށް، އެކަލާނގެ، ތިބާ، تركيب ކުރެއްވިއެވެ.","translator":"Office of the President of Maldives"},{"aya":"009","id":5838,"locale":"dv","sura":"082","text":"ހަމަހިލާ އެހެންނަކުން ނުވާނެއެވެ. އަދި ކިއެއްތަ! (قيامة ދުވަހުން) ޖަޒާ ދެއްވާނޭކަން ތިޔަބައިމީހުން ދޮގުކުރަމުއެވެ.","translator":"Office of the President of Maldives"},{"aya":"010","id":5839,"locale":"dv","sura":"082","text":"އަދި ހަމަކަށަވަރުން، ތިޔަބައިމީހުންގެ މައްޗަށް ރައްކާތެރިވެ ބަލަހައްޓަވާ ملائكة ންވެއެވެ.","translator":"Office of the President of Maldives"},{"aya":"011","id":5840,"locale":"dv","sura":"082","text":"(އެއީ) މާތްވެގެންވާ، ލިޔުއްވާ ملائكة ންނެވެ.","translator":"Office of the President of Maldives"},{"aya":"012","id":5841,"locale":"dv","sura":"082","text":"ތިޔަބައިމީހުން ކުރާ ކަންތައް އެ ملائكة ން ދެނެވަޑައިގެންވެތެވެ.","translator":"Office of the President of Maldives"},{"aya":"013","id":5842,"locale":"dv","sura":"082","text":"ހަމަކަށަވަރުން، ހެޔޮލަފާ މީހުންވަނީ، نعمة ގެ ސުވަރުގޭގައިކަން ކަށަވަރެވެ.","translator":"Office of the President of Maldives"},{"aya":"014","id":5843,"locale":"dv","sura":"082","text":"އަދި ހަމަކަށަވަރުން، كافر ންވަނީ، ނަރަކައިގައިކަން ކަށަވަރެވެ.","translator":"Office of the President of Maldives"}],"metadata":{"itemsPerPage":7,"pages":3,"previousPage":"/dv/s082.json","nextPage":"/dv/s082-3.json"}}