{"results":[{"aya":"015","id":5338,"locale":"cs","sura":"069","text":"v ten den nezvratná dopadne","translator":"Preklad I. Hrbek"},{"aya":"016","id":5339,"locale":"cs","sura":"069","text":"a nebe se rozpoltí a bude zející toho dne","translator":"Preklad I. Hrbek"},{"aya":"017","id":5340,"locale":"cs","sura":"069","text":"a stát budou andělé na krajích jeho; v ten den osm jich nad sebou ponese trůn Pána tvého.","translator":"Preklad I. Hrbek"},{"aya":"018","id":5341,"locale":"cs","sura":"069","text":"V ten den předvedeni budete a nezůstane u vás skryto nic tajného.","translator":"Preklad I. Hrbek"},{"aya":"019","id":5342,"locale":"cs","sura":"069","text":"A komu bude dána kniha jeho do pravice, ten řekne: \"Zde přečtěte si knihu mou!","translator":"Preklad I. Hrbek"},{"aya":"020","id":5343,"locale":"cs","sura":"069","text":"Já soudil jsem vždy, že s účtem svým se setkám jednou.\"","translator":"Preklad I. Hrbek"},{"aya":"021","id":5344,"locale":"cs","sura":"069","text":"A takový bude mít žití příjemné","translator":"Preklad I. Hrbek"}],"metadata":{"itemsPerPage":7,"pages":8,"previousPage":"/cs/s069-2.json","nextPage":"/cs/s069-4.json"}}