{"results":[{"aya":"043","id":336,"locale":"ja","sura":"003","text":"「マルヤムよ，あなたの主に崇敬の誠を棒げてサジダしなさい。ルクーウ（立礼）するものと一緒にルクーウしなさい。」","translator":"Unknown"},{"aya":"044","id":337,"locale":"ja","sura":"003","text":"これは幽玄界の消息の一部であり，われはこれをあなたに啓示する。かれらが(篆?)矢を投げて誰がマルヤムを養育すべきかを決めた時，あなたはかれらの中にいなかった。またかれらが相争った時も，あなたはかれらと一緒ではなかった。","translator":"Unknown"},{"aya":"045","id":338,"locale":"ja","sura":"003","text":"また天使たちがこう言った時を思え。「マルヤムよ，本当にアッラーは直接ご自身の御言葉で，あなたに吉報を伝えられる。マルヤムの子，その名はマスィーフ・イーサー，かれは現世でも来世でも高い栄誉を得，また（アッラーの）側近の一人であろう。","translator":"Unknown"},{"aya":"046","id":339,"locale":"ja","sura":"003","text":"かれは揺り籠の中でも，また成入してからも人びとに語り，正しい者の一人である。」","translator":"Unknown"},{"aya":"047","id":340,"locale":"ja","sura":"003","text":"かの女は言った。「主よ，誰もわたしに触れたことはありません。どうしてあたしに子が出来ましょうか。」かれ（天使）は言った。「このように，アッラーは御望みのものを御創りになられる。かれが一事を決められ，『有れ。』と仰せになれば即ち有るのである。」","translator":"Unknown"},{"aya":"048","id":341,"locale":"ja","sura":"003","text":"主は啓典と英知と律法と福音とをかれに教えられ，","translator":"Unknown"},{"aya":"049","id":342,"locale":"ja","sura":"003","text":"そしてかれを，イスラエルの子孫への使徒とされた。（イーサーは言った。）「わたしは，あなたがたの主から，印を(西?)したのである。わたしはあなたがたのために，泥で鳥の形を造り，それに息を吹き込めば，アッラーの御許しによりそれは鳥になる。またアッラーの御許しによって，生れ付きの盲人や，願患者を治し，また死者を生き返らせる。またわたしは，あなたがたが何を食べ，何を家に蓄えているかを告げよう。もしあなたがたが（真の）信者なら，その中にあなたがたへの印がある。","translator":"Unknown"}],"metadata":{"itemsPerPage":7,"pages":29,"previousPage":"/ja/s003-6.json","nextPage":"/ja/s003-8.json"}}