{"results":[{"aya":"015","id":4916,"locale":"ja","sura":"055","text":"また火の炎からジン（幽精）を創られた。","translator":"Unknown"},{"aya":"016","id":4917,"locale":"ja","sura":"055","text":"それであなたがたは，主の恩恵のどれを嘘と言うのか。","translator":"Unknown"},{"aya":"017","id":4918,"locale":"ja","sura":"055","text":"（かれは） 2つの東の主であり，また2つの西の主であられる。","translator":"Unknown"},{"aya":"018","id":4919,"locale":"ja","sura":"055","text":"それであなたがたは，主の恩恵のどれを嘘と言うのか。","translator":"Unknown"},{"aya":"019","id":4920,"locale":"ja","sura":"055","text":"かれは2つの海を一緒に合流させられる。","translator":"Unknown"},{"aya":"020","id":4921,"locale":"ja","sura":"055","text":"（だが）両者の間には，（アッラーの配慮によって）障壁があリ一方が他方を制圧することはない。","translator":"Unknown"},{"aya":"021","id":4922,"locale":"ja","sura":"055","text":"それであなたがたは，主の恩恵のどれを嘘と言うのか。","translator":"Unknown"}],"metadata":{"itemsPerPage":7,"pages":12,"previousPage":"/ja/s055-2.json","nextPage":"/ja/s055-4.json"}}