{"results":[{"aya":"015","id":4750,"locale":"en","sura":"052","text":"Then is this magic, or do you not see?","translator":"Saheeh International"},{"aya":"016","id":4751,"locale":"en","sura":"052","text":"[Enter to] burn therein; then be patient or impatient - it is all the same for you. You are only being recompensed [for] what you used to do.\"","translator":"Saheeh International"},{"aya":"017","id":4752,"locale":"en","sura":"052","text":"Indeed, the righteous will be in gardens and pleasure,","translator":"Saheeh International"},{"aya":"018","id":4753,"locale":"en","sura":"052","text":"Enjoying what their Lord has given them, and their Lord protected them from the punishment of Hellfire.","translator":"Saheeh International"},{"aya":"019","id":4754,"locale":"en","sura":"052","text":"[They will be told], \"Eat and drink in satisfaction for what you used to do.\"","translator":"Saheeh International"},{"aya":"020","id":4755,"locale":"en","sura":"052","text":"They will be reclining on thrones lined up, and We will marry them to fair women with large, [beautiful] eyes.","translator":"Saheeh International"},{"aya":"021","id":4756,"locale":"en","sura":"052","text":"And those who believed and whose descendants followed them in faith - We will join with them their descendants, and We will not deprive them of anything of their deeds. Every person, for what he earned, is retained.","translator":"Saheeh International"}],"metadata":{"itemsPerPage":7,"pages":7,"previousPage":"/en/s052-2.json","nextPage":"/en/s052-4.json"}}