{"results":[{"aya":"008","id":6087,"locale":"ps","sura":"093","text":"او ته يې فقیر وموندلې، نو غني يې كړې","translator":"Abdulwali Khan"},{"aya":"009","id":6088,"locale":"ps","sura":"093","text":"نو هر چې یتیم دى، نو ته (ده ته) قهر مه كوه","translator":"Abdulwali Khan"},{"aya":"010","id":6089,"locale":"ps","sura":"093","text":"او هر چې سوالګرى دى، نو ته يې مه رټه","translator":"Abdulwali Khan"},{"aya":"011","id":6090,"locale":"ps","sura":"093","text":"او پاتې شو (نعمت) نو ته د خپل رب نعمت بیانوه","translator":"Abdulwali Khan"}],"metadata":{"itemsPerPage":7,"pages":2,"previousPage":"/ps/s093.json"}}