{"results":[{"aya":"001","id":6231,"locale":"ps","sura":"114","text":"(اى نبي) ته ووایه: زه د خلقو په رب پورې پناه نیسم","translator":"Abdulwali Khan"},{"aya":"002","id":6232,"locale":"ps","sura":"114","text":"چې د خلقو بادشاه دى","translator":"Abdulwali Khan"},{"aya":"003","id":6233,"locale":"ps","sura":"114","text":"د خلقو (حقیقي) معبود دى","translator":"Abdulwali Khan"},{"aya":"004","id":6234,"locale":"ps","sura":"114","text":"له شره د وسوسې اچوونكي، تښتېدونكي","translator":"Abdulwali Khan"},{"aya":"005","id":6235,"locale":"ps","sura":"114","text":"هغه چې د خلقو په سینو كې وسوسې اچوي","translator":"Abdulwali Khan"},{"aya":"006","id":6236,"locale":"ps","sura":"114","text":"چی (دغه وسوسې اچوونكي) له پېریانو او انسانانو ځنې دي","translator":"Abdulwali Khan"}],"metadata":{"itemsPerPage":7,"pages":1}}