{"results":[{"aya":"022","id":5734,"locale":"ru","sura":"079","text":"Потом Фараон отвернулся от Мусы, упорствуя в своём сопротивлении ему.","translator":"Ministry of Awqaf, Egypt"},{"aya":"023","id":5735,"locale":"ru","sura":"079","text":"И, собрав колдунов и людей,","translator":"Ministry of Awqaf, Egypt"},{"aya":"024","id":5736,"locale":"ru","sura":"079","text":"возгласил: \"Я - ваш высочайший бог!\"","translator":"Ministry of Awqaf, Egypt"},{"aya":"025","id":5737,"locale":"ru","sura":"079","text":"Аллах подверг его наказанию за эти последние его слова \"Я - ваш высочайший бог!\" и за предыдущие слова, когда он объявил Мусу - да будет над ним мир! - лжецом.","translator":"Ministry of Awqaf, Egypt"},{"aya":"026","id":5738,"locale":"ru","sura":"079","text":"Поистине, в этом рассказе - назидание для богобоязненных.","translator":"Ministry of Awqaf, Egypt"},{"aya":"027","id":5739,"locale":"ru","sura":"079","text":"Что было труднее - создать вас, о вы, отрицающие воскрешение, или небо?! Он соединил его разъединённые части","translator":"Ministry of Awqaf, Egypt"},{"aya":"028","id":5740,"locale":"ru","sura":"079","text":"и поднял свод, и возвысил его над вами, и сделал его ровным со всех сторон и совершенным.","translator":"Ministry of Awqaf, Egypt"}],"metadata":{"itemsPerPage":7,"pages":7,"previousPage":"/ru/s079-3.json","nextPage":"/ru/s079-5.json"}}