{"results":[{"aya":"001","id":5713,"locale":"sw","sura":"079","text":"Naapa kwa wanao komoa kwa nguvu,","translator":"Ali Muhsin Al-Barwani"},{"aya":"002","id":5714,"locale":"sw","sura":"079","text":"Na kwa wanao toa kwa upole,","translator":"Ali Muhsin Al-Barwani"},{"aya":"003","id":5715,"locale":"sw","sura":"079","text":"Na wanao ogelea,","translator":"Ali Muhsin Al-Barwani"},{"aya":"004","id":5716,"locale":"sw","sura":"079","text":"Wakishindana mbio,","translator":"Ali Muhsin Al-Barwani"},{"aya":"005","id":5717,"locale":"sw","sura":"079","text":"Wakidabiri mambo.","translator":"Ali Muhsin Al-Barwani"},{"aya":"006","id":5718,"locale":"sw","sura":"079","text":"Siku kitapo tetemeka cha kutetemeka,","translator":"Ali Muhsin Al-Barwani"},{"aya":"007","id":5719,"locale":"sw","sura":"079","text":"Kifuate cha kufuatia.","translator":"Ali Muhsin Al-Barwani"}],"metadata":{"itemsPerPage":7,"pages":7,"nextPage":"/sw/s079-2.json"}}