{"results":[{"aya":"001","id":4902,"locale":"zh","sura":"055","text":"至仁主，","translator":"Ma Jian"},{"aya":"002","id":4903,"locale":"zh","sura":"055","text":"曾教授《古兰经》，","translator":"Ma Jian"},{"aya":"003","id":4904,"locale":"zh","sura":"055","text":"他创造了人，","translator":"Ma Jian"},{"aya":"004","id":4905,"locale":"zh","sura":"055","text":"并教人修辞。","translator":"Ma Jian"},{"aya":"005","id":4906,"locale":"zh","sura":"055","text":"日月是依定数而运行的。","translator":"Ma Jian"},{"aya":"006","id":4907,"locale":"zh","sura":"055","text":"草木是顺从他的意旨的。","translator":"Ma Jian"},{"aya":"007","id":4908,"locale":"zh","sura":"055","text":"他曾将天升起。他曾规定公平，","translator":"Ma Jian"}],"metadata":{"itemsPerPage":7,"pages":12,"nextPage":"/zh/s055-2.json"}}