{"results":[{"aya":"008","id":5196,"locale":"bn","sura":"063","text":"তারাই বলেঃ আমরা যদি মদীনায় প্রত্যাবর্তন করি তবে সেখান থেকে সবল অবশ্যই দুর্বলকে বহিস্কৃত করবে। শক্তি তো আল্লাহ তাঁর রসূল ও মুমিনদেরই কিন্তু মুনাফিকরা তা জানে না।","translator":"Muhiuddin Khan"},{"aya":"009","id":5197,"locale":"bn","sura":"063","text":"মুমিনগণ! তোমাদের ধন-সম্পদ ও সন্তান-সন্ততি যেন তোমাদেরকে আল্লাহর স্মরণ থেকে গাফেল না করে। যারা এ কারণে গাফেল হয়, তারাই তো ক্ষতিগ্রস্ত।","translator":"Muhiuddin Khan"},{"aya":"010","id":5198,"locale":"bn","sura":"063","text":"আমি তোমাদেরকে যা দিয়েছি, তা থেকে মৃত্যু আসার আগেই ব্যয় কর। অন্যথায় সে বলবেঃ হে আমার পালনকর্তা, আমাকে আরও কিছুকাল অবকাশ দিলে না কেন? তাহলে আমি সদকা করতাম এবং সৎকর্মীদের অন্তর্ভুক্ত হতাম।","translator":"Muhiuddin Khan"},{"aya":"011","id":5199,"locale":"bn","sura":"063","text":"প্রত্যেক ব্যক্তির নির্ধারিত সময় যখন উপস্থিত হবে, তখন আল্লাহ কাউকে অবকাশ দেবেন না। তোমরা যা কর, আল্লাহ সে বিষয়ে খবর রাখেন।","translator":"Muhiuddin Khan"}],"metadata":{"itemsPerPage":7,"pages":2,"previousPage":"/bn/s063.json"}}