{"results":[{"aya":"036","id":2968,"locale":"az","sura":"026","text":"Onlar dedilər: “Onu qardaşı ilə bir qədər gözlət və şəhərlərə adam yığanlar göndər ki,","translator":"Alikhan Musayev"},{"aya":"037","id":2969,"locale":"az","sura":"026","text":"bütün bilikli sehrbazları sənin yanına gətirsinlər”.","translator":"Alikhan Musayev"},{"aya":"038","id":2970,"locale":"az","sura":"026","text":"Beləliklə, sehrbazlar bəlli bir günün müəyyən edilmiş vaxtında toplandılar.","translator":"Alikhan Musayev"},{"aya":"039","id":2971,"locale":"az","sura":"026","text":"Camaata deyildi: “Siz də yığışırsınızmı?","translator":"Alikhan Musayev"},{"aya":"040","id":2972,"locale":"az","sura":"026","text":"Əgər sehrbazlar qalib gəlsələr, ola bilsin ki, biz də onlara tabe olaq”.","translator":"Alikhan Musayev"},{"aya":"041","id":2973,"locale":"az","sura":"026","text":"Sehrbazlar gələn kimi Firona dedilər: “Əgər qalib gəlsək, bizə mükafat veriləcəkmi?”","translator":"Alikhan Musayev"},{"aya":"042","id":2974,"locale":"az","sura":"026","text":"Firon dedi: “Bəli! Belə olacağı təqdirdə sizi özümə yaxın adamlardan edəcəyəm”.","translator":"Alikhan Musayev"}],"metadata":{"itemsPerPage":7,"pages":33,"previousPage":"/az/s026-5.json","nextPage":"/az/s026-7.json"}}