{"results":[{"aya":"022","id":5644,"locale":"az","sura":"077","text":"məlum bir vaxta kimi?","translator":"Alikhan Musayev"},{"aya":"023","id":5645,"locale":"az","sura":"077","text":"Biz nütfəni yaratmağa qadir olduq. Nə gözəl Qadir olanlarıq Biz!","translator":"Alikhan Musayev"},{"aya":"024","id":5646,"locale":"az","sura":"077","text":"Qiyaməti yalan sayanların o gün vay halına!","translator":"Alikhan Musayev"},{"aya":"025","id":5647,"locale":"az","sura":"077","text":"Məgər Biz yeri məskən etmədikmi –","translator":"Alikhan Musayev"},{"aya":"026","id":5648,"locale":"az","sura":"077","text":"dirilər və ölülərə?","translator":"Alikhan Musayev"},{"aya":"027","id":5649,"locale":"az","sura":"077","text":"Orada möhkəm dayanan uca dağlar yaratmadıqmı və sizə şirin sulardan içirtmədikmi?","translator":"Alikhan Musayev"},{"aya":"028","id":5650,"locale":"az","sura":"077","text":"Qiyaməti yalan sayanların o gün vay halına!","translator":"Alikhan Musayev"}],"metadata":{"itemsPerPage":7,"pages":8,"previousPage":"/az/s077-3.json","nextPage":"/az/s077-5.json"}}