{"results":[{"aya":"092","id":1894,"locale":"it","sura":"015","text":"per il tuo Signore, tutti li interrogheremo","translator":"Hamza Roberto Piccardo"},{"aya":"093","id":1895,"locale":"it","sura":"015","text":"a proposito di quello che facevano.","translator":"Hamza Roberto Piccardo"},{"aya":"094","id":1896,"locale":"it","sura":"015","text":"Proclama con forza quello che ti è stato ordinato e rifuggi dagli associatori.","translator":"Hamza Roberto Piccardo"},{"aya":"095","id":1897,"locale":"it","sura":"015","text":"Noi ti bastiamo contro chi ti schernisce,","translator":"Hamza Roberto Piccardo"},{"aya":"096","id":1898,"locale":"it","sura":"015","text":"[contro] coloro che affiancano ad Allah un'altra divinità. Presto sapranno.","translator":"Hamza Roberto Piccardo"},{"aya":"097","id":1899,"locale":"it","sura":"015","text":"Ben sappiamo che il tuo petto si affligge per quello che dicono.","translator":"Hamza Roberto Piccardo"},{"aya":"098","id":1900,"locale":"it","sura":"015","text":"Glorifica il tuo Signore lodandoLo e sii tra coloro che si prosternano,","translator":"Hamza Roberto Piccardo"}],"metadata":{"itemsPerPage":7,"pages":15,"previousPage":"/it/s015-13.json","nextPage":"/it/s015-15.json"}}