{"results":[{"aya":"022","id":4806,"locale":"it","sura":"053","text":"Che ingiusta spartizione!","translator":"Hamza Roberto Piccardo"},{"aya":"023","id":4807,"locale":"it","sura":"053","text":"Non sono altro che nomi menzionati da voi e dai vostri antenati, a proposito dei quali Allah non fece scendere nessuna autorità. Essi si abbandonano alle congetture e a quello che affascina gli animi loro, nonostante sia giunta loro una guida del loro Signore.","translator":"Hamza Roberto Piccardo"},{"aya":"024","id":4808,"locale":"it","sura":"053","text":"L'uomo otterrà forse tutto quel che desidera?","translator":"Hamza Roberto Piccardo"},{"aya":"025","id":4809,"locale":"it","sura":"053","text":"Appartengono ad Allah l'altra vita e questa vita.","translator":"Hamza Roberto Piccardo"},{"aya":"026","id":4810,"locale":"it","sura":"053","text":"Quanti angeli nel cielo, la cui intercessione sarà vana finché Allah non l'abbia permessa, e in favore di chi Egli voglia e di chi Gli aggrada.","translator":"Hamza Roberto Piccardo"},{"aya":"027","id":4811,"locale":"it","sura":"053","text":"Invero quelli che non credono nell'altra vita danno agli angeli nomi femminili,","translator":"Hamza Roberto Piccardo"},{"aya":"028","id":4812,"locale":"it","sura":"053","text":"mentre non posseggono alcuna scienza: si abbandonano alle congetture, ma la congettura non può nulla contro la verità.","translator":"Hamza Roberto Piccardo"}],"metadata":{"itemsPerPage":7,"pages":9,"previousPage":"/it/s053-3.json","nextPage":"/it/s053-5.json"}}