{"results":[{"aya":"043","id":1845,"locale":"nl","sura":"015","text":"En voorwaar, de Het is aan hen allen zeker toegezegd.","translator":"Sofian S. Siregar"},{"aya":"044","id":1846,"locale":"nl","sura":"015","text":"Zij heeft zeven poorten. Aan iedere poort is een deel van hen toegewezen.","translator":"Sofian S. Siregar"},{"aya":"045","id":1847,"locale":"nl","sura":"015","text":"Voorwaar, de Moettaqoen zullen in de Tuinen (het Paradijs) en bij bronnen vertoeven.","translator":"Sofian S. Siregar"},{"aya":"046","id":1848,"locale":"nl","sura":"015","text":"(Tegen hen wordt gezegd:) \"Treedt deze binnen in vrede en veiligheid.\"","translator":"Sofian S. Siregar"},{"aya":"047","id":1849,"locale":"nl","sura":"015","text":"En Wij nemen weg wat er in hun harten aan wrok is, (zij zijn daarin) als broeders, op rustbanken zitten zij tegenover elkaar.","translator":"Sofian S. Siregar"},{"aya":"048","id":1850,"locale":"nl","sura":"015","text":"Daarin raakt hen geen vermoeidheid en zij worden daaruit niet verdreven.","translator":"Sofian S. Siregar"},{"aya":"049","id":1851,"locale":"nl","sura":"015","text":"Bericht mijn dienaren (O Moehammad:) \"Voorwaar, ik ben de Vergevensgezinde, de meest Barmhartige.","translator":"Sofian S. Siregar"}],"metadata":{"itemsPerPage":7,"pages":15,"previousPage":"/nl/s015-6.json","nextPage":"/nl/s015-8.json"}}