{"results":[{"aya":"085","id":5064,"locale":"ha","sura":"056","text":"Kuma Mũ ne mafi kusanta gare shi daga gare ku, to, amma kũ bã ku gani.","translator":"Abubakar Mahmoud Gumi"},{"aya":"086","id":5065,"locale":"ha","sura":"056","text":"To, don me in dai kun kasance bã waɗanda zã a yi wa sakamako ba?","translator":"Abubakar Mahmoud Gumi"},{"aya":"087","id":5066,"locale":"ha","sura":"056","text":"Ku mayar da shi (cikin jikinsa) har idan kun kasance mãsu gaskiya.","translator":"Abubakar Mahmoud Gumi"},{"aya":"088","id":5067,"locale":"ha","sura":"056","text":"To, amma idan (mai mutuwar) ya kasance daga makusanta,","translator":"Abubakar Mahmoud Gumi"},{"aya":"089","id":5068,"locale":"ha","sura":"056","text":"Sai hũtawa da kyakkyawan abinci da Aljannar ni'ima.","translator":"Abubakar Mahmoud Gumi"},{"aya":"090","id":5069,"locale":"ha","sura":"056","text":"Kuma amma idan ya kasance daga mazõwa dãma,","translator":"Abubakar Mahmoud Gumi"},{"aya":"091","id":5070,"locale":"ha","sura":"056","text":"Sai (a ce masa) aminci ya tabbata a gare ka daga mazõwa dãma.","translator":"Abubakar Mahmoud Gumi"}],"metadata":{"itemsPerPage":7,"pages":14,"previousPage":"/ha/s056-12.json","nextPage":"/ha/s056-14.json"}}