{"results":[{"aya":"015","id":22,"locale":"ber","sura":"002","text":"Öebbi ad Ittihi fellasen. Isnerna yasen lbwe$v nnsen; ddebdeben.","translator":"Ramdane At Mansour"},{"aya":"016","id":23,"locale":"ber","sura":"002","text":"Widak, d wid iu$en ttelfan s nnhaya; ur d issasay ssuq nnsen, ur pwanhan.","translator":"Ramdane At Mansour"},{"aya":"017","id":24,"locale":"ber","sura":"002","text":"Tevôa yidsen am win issa$en times. Mi tnewweô ayen i s d izzin, Öebbi Iddem tafat nnsen, Iooa ten di tillas, ur pwalin.","translator":"Ramdane At Mansour"},{"aya":"018","id":25,"locale":"ber","sura":"002","text":"Âaégen, gugmen, dre$len; ihi, nitni ur d ppu$alen s abrid.","translator":"Ramdane At Mansour"},{"aya":"019","id":26,"locale":"ber","sura":"002","text":"Ne$ am usigna igenni, degs tillas, tirmegt, lebôaq. Pparran ivudan nnsen deg imeééu$en nnsen, mgal ssiâqat; ad nnestaôen si tmeppant. Öebbi Izzi i ijehliyen.","translator":"Ramdane At Mansour"},{"aya":"020","id":27,"locale":"ber","sura":"002","text":"Qôib i sen iêwi lebôaq, iéôi. Yal tikelt ideg i sen icâal, ad ddun syis. Mi sen ixsi, ad êebsen. Ma ihwa yaS i Öebbi, ad asen Ikkes timesliwt akked yiéôi nnsen. Öebbi, s tidep, Izmer i yal cci.","translator":"Ramdane At Mansour"},{"aya":"021","id":28,"locale":"ber","sura":"002","text":"A yimdanen! Âabdet Mass nnwen ikwen Ixelqen, kunwi, akked wid i kwen id izwaren, amar a pêezzbem;","translator":"Ramdane At Mansour"}],"metadata":{"itemsPerPage":7,"pages":41,"previousPage":"/ber/s002-2.json","nextPage":"/ber/s002-4.json"}}