{"results":[{"aya":"043","id":3383,"locale":"ber","sura":"029","text":"Imedyaten agi, Neppawi ten id, i l$aci. Siwa imusnawen ara ten ifehmen.","translator":"Ramdane At Mansour"},{"aya":"044","id":3384,"locale":"ber","sura":"029","text":"Ixleq Öebbi tamurt akked igenwan, s tidep. Ih, deg waya, assekni i lmumnin.","translator":"Ramdane At Mansour"},{"aya":"045","id":3385,"locale":"ber","sura":"029","text":"Mel ayen i k id ippuweêêan si Tezmamt. Bedd i téallit. Ih, taéallit teppekkes lâaô, tuccva. War ccek, iugar ip usmekti n Öebbi. Öebbi Iéôa acu tûenâam.","translator":"Ramdane At Mansour"},{"aya":"046","id":3386,"locale":"ber","sura":"029","text":"Ur pnamaret At Tezmamt, siwa s wawal aéidan, siwa wid degsen idensen. Init: \"numen s wayen id irsen $uône$, id irsen $uôwen. Öebbi nne$, akked Öebbi nnwen, Yiwen. Nekwni $uôeS d imvuâen\".","translator":"Ramdane At Mansour"},{"aya":"047","id":3387,"locale":"ber","sura":"029","text":"Akka ay ed Nessers, $uôek, Tazmamt. Wid iwumi Nefka Tazmamt, umnen yis. Ger wigi, kra umnen yis. I inekôen issekniyen nne£, siwa ijehliyen.","translator":"Ramdane At Mansour"},{"aya":"048","id":3388,"locale":"ber","sura":"029","text":"Ur telliv temmalev kra n Tezmamt, uqbel tagi; ur p tepparuv, s uyeffus ik. Yili ad cukken inekkaôen.","translator":"Ramdane At Mansour"},{"aya":"049","id":3389,"locale":"ber","sura":"029","text":"Xaîi, neppa d issekniyen iberrzen, deg idmaren n wid iwumi teppunefk tmusni. Siwa imednas, i inekôen issekniyen nne£.","translator":"Ramdane At Mansour"}],"metadata":{"itemsPerPage":7,"pages":10,"previousPage":"/ber/s029-6.json","nextPage":"/ber/s029-8.json"}}