{"results":[{"aya":"113","id":2786,"locale":"so","sura":"023","text":"Waxayna Odhan waxaan ku Nagaanay Maalin ama Maalin Qaarkeed, warsada kuwa wax tiriya «Malaa'gta».","translator":"Mahmud Muhammad Abduh"},{"aya":"114","id":2787,"locale":"so","sura":"023","text":"Wuxuu Yidhi Maydaan Nagaanin wax Yar Mooyee Haddaad wax Ogtihiin.","translator":"Mahmud Muhammad Abduh"},{"aya":"115","id":2788,"locale":"so","sura":"023","text":"ma Waxaad u Malayseen inaan Idiin Abuuray Ciyaar oon idinka Xagganaga loo soo Celinayn.","translator":"Mahmud Muhammad Abduh"},{"aya":"116","id":2789,"locale":"so","sura":"023","text":"Waxaa Sarreeya Eebaha Xaakimka Xaqa ah Ilaah aan isaga ahayna ma jiro Waana Eebaha Carshiga Sharafta leh.","translator":"Mahmud Muhammad Abduh"},{"aya":"117","id":2790,"locale":"so","sura":"023","text":"Ciddii Caabudda Eebe la Jirkiisa Ilaah kale oon Xujo lahayn Xisaabtiisu waa uun Eebe Agtiisa, mana Liibaanto Gaalo.","translator":"Mahmud Muhammad Abduh"},{"aya":"118","id":2791,"locale":"so","sura":"023","text":"Waxaad Dhahdaa Eebow Dhaaf oo Naxariiso adaa Naxariiste u Khayr Roone.","translator":"Mahmud Muhammad Abduh"}],"metadata":{"itemsPerPage":7,"pages":17,"previousPage":"/so/s023-16.json"}}