{"results":[{"aya":"001","id":5552,"locale":"ro","sura":"075","text":"Nu! Jur pe Ziua Învierii!","translator":"George Grigore"},{"aya":"002","id":5553,"locale":"ro","sura":"075","text":"Nu! Jur pe sufletul mereu-dojenitor!","translator":"George Grigore"},{"aya":"003","id":5554,"locale":"ro","sura":"075","text":"Omul socoate că nu-i vom strânge la un loc oasele?","translator":"George Grigore"},{"aya":"004","id":5555,"locale":"ro","sura":"075","text":"Ba da! Noi avem putinţa de a-i potrivi şi oscioarele degetelor sale.","translator":"George Grigore"},{"aya":"005","id":5556,"locale":"ro","sura":"075","text":"Înainte de aceasta însă, omul doreşte întotdeauna desfrâul.","translator":"George Grigore"},{"aya":"006","id":5557,"locale":"ro","sura":"075","text":"El întreabă: “Când va veni Ziua Învierii?”","translator":"George Grigore"},{"aya":"007","id":5558,"locale":"ro","sura":"075","text":"Atunci când vederea fi-va fulgerată,","translator":"George Grigore"}],"metadata":{"itemsPerPage":7,"pages":6,"nextPage":"/ro/s075-2.json"}}