{"results":[{"aya":"106","id":2779,"locale":"sq","sura":"023","text":"Do të thonë ata: “O Zoti ynë, neve na ka munduar e keqja jonë, andaj jemi bërë popull i humbur.","translator":"Hasan Efendi Nahi"},{"aya":"107","id":2780,"locale":"sq","sura":"023","text":"O Zoti ynë, nxirrna prej tij (zjarrit); e nëse na kthehemi (në mohim), (atëherë) do të jemi zullumqarë”.","translator":"Hasan Efendi Nahi"},{"aya":"108","id":2781,"locale":"sq","sura":"023","text":"(Perëndia) do të thotë: “Rrini në të (zjarr) të përbuzur dhe mos Më flisni asgjë!”","translator":"Hasan Efendi Nahi"},{"aya":"109","id":2782,"locale":"sq","sura":"023","text":"Ka qenë një grup i robërve të Mi, i cili thoshte: “O Zoti ynë, na kemi besuar, andaj na falë dhe na mëshiro! E, Ti je më i miri mëshirues!” –","translator":"Hasan Efendi Nahi"},{"aya":"110","id":2783,"locale":"sq","sura":"023","text":"e ju i keni marrë ata për (objekt) talljeje, andaj, për këtë shkak, Mua, më harruat së përmenduri, e përherë i përqeshnit ata.","translator":"Hasan Efendi Nahi"},{"aya":"111","id":2784,"locale":"sq","sura":"023","text":"Unë, i kam shpërblyer ata sot, për durueshmërinë e tyre, e ata, me të vërtetë, janë të shpëtuar.","translator":"Hasan Efendi Nahi"},{"aya":"112","id":2785,"locale":"sq","sura":"023","text":"(Engjëlli) do të thotë: “Sa vjet i keni kaluar në Tokë (botë)?”","translator":"Hasan Efendi Nahi"}],"metadata":{"itemsPerPage":7,"pages":17,"previousPage":"/sq/s023-15.json","nextPage":"/sq/s023-17.json"}}