{"results":[{"aya":"029","id":5300,"locale":"pl","sura":"068","text":"Powiedzieli: \"Chwała niech będzie naszemu Panu! Zaprawdę, byliśmy niesprawiedliwi!\"","translator":"Józefa Bielawskiego"},{"aya":"030","id":5301,"locale":"pl","sura":"068","text":"Wtedy oni zwrócili się jeden do drugiego, ganiąc się wzajemnie.","translator":"Józefa Bielawskiego"},{"aya":"031","id":5302,"locale":"pl","sura":"068","text":"Mówili: \"Biada nam! Zaprawdę, byliśmy buntownikami!","translator":"Józefa Bielawskiego"},{"aya":"032","id":5303,"locale":"pl","sura":"068","text":"Lecz, być może, nasz Pan da nam w zamian coś lepszego od niego. Zaprawdę, my do naszego Pana kierujemy nasze pragnienia!\"","translator":"Józefa Bielawskiego"},{"aya":"033","id":5304,"locale":"pl","sura":"068","text":"Taka jest kara! Lecz kara życia ostatecznego jest większa. O, gdybyście wiedzieli!","translator":"Józefa Bielawskiego"},{"aya":"034","id":5305,"locale":"pl","sura":"068","text":"Zaprawdę, dla ludzi bogobojnych u Pana są Ogrody Szczęśliwości!","translator":"Józefa Bielawskiego"},{"aya":"035","id":5306,"locale":"pl","sura":"068","text":"Czyż My potraktujemy tych, którzy poddali się całkowicie, tak jak grzeszników?","translator":"Józefa Bielawskiego"}],"metadata":{"itemsPerPage":7,"pages":8,"previousPage":"/pl/s068-4.json","nextPage":"/pl/s068-6.json"}}