{"results":[{"aya":"001","id":5376,"locale":"pl","sura":"070","text":"Zapytał żądający wyjaśnienia o karę spadającą","translator":"Józefa Bielawskiego"},{"aya":"002","id":5377,"locale":"pl","sura":"070","text":"Na niewiernych - której nikt oddalić nie potrafi -","translator":"Józefa Bielawskiego"},{"aya":"003","id":5378,"locale":"pl","sura":"070","text":"Pochodzącą od Boga, władcy stopni.","translator":"Józefa Bielawskiego"},{"aya":"004","id":5379,"locale":"pl","sura":"070","text":"Aniołowie i Duch wznoszą się ku Niemu w Dniu, którego wielkość - pięćdziesiąt tysięcy lat.","translator":"Józefa Bielawskiego"},{"aya":"005","id":5380,"locale":"pl","sura":"070","text":"Bądź więc cierpliwy cierpliwością piękną!","translator":"Józefa Bielawskiego"},{"aya":"006","id":5381,"locale":"pl","sura":"070","text":"Oni myślą, że ona jest daleka,","translator":"Józefa Bielawskiego"},{"aya":"007","id":5382,"locale":"pl","sura":"070","text":"Lecz My sądzimy, że jest bliska.","translator":"Józefa Bielawskiego"}],"metadata":{"itemsPerPage":7,"pages":7,"nextPage":"/pl/s070-2.json"}}